pytempo/__init__.py
pytempo/main.py
pytempo-0.3.0.dist-info/METADATA
pytempo-0.3.0.dist-info/entry_points.txt
pytempo-0.3.0.dist-info/WHEEL
pytempo-0.3.0.dist-info/RECORD
