Metadata-Version: 2.1
Name: pytempo
Version: 0.3.0
Summary: 
Author: Sebastian Blum
Author-email: sebast.blum@gmail.com
Requires-Python: >=3.11,<4.0
Classifier: Programming Language :: Python :: 3
Classifier: Programming Language :: Python :: 3.11
Requires-Dist: click (>=8.1.3,<9.0.0)
Requires-Dist: datetime (>=5.0,<6.0)
Requires-Dist: openpyxl (>=3.1.0,<4.0.0)
Requires-Dist: pandas (>=1.5.3,<2.0.0)
Requires-Dist: xlrd (>=2.0.1,<3.0.0)
